mw_python_sdk/__init__.py
mw_python_sdk/api.py
mw_python_sdk/api_list.py
mw_python_sdk/bin/mwcli.py
mw_python_sdk/core.py
mw_python_sdk/frp/__init__.py
mw_python_sdk/fs.py
mw_python_sdk/llm/README.md
mw_python_sdk/llm/__init__.py
mw_python_sdk/llm/bench.py
mw_python_sdk/llm/echo_server.py
mw_python_sdk/llm/inference.py
mw_python_sdk/llm/model.py
mw_python_sdk/llm/monitor.py
mw_python_sdk/llm/plot.py
mw_python_sdk/rag.py
mw_python_sdk/utils.py
mw_python_sdk-0.0.93.dist-info/METADATA
mw_python_sdk-0.0.93.dist-info/WHEEL
mw_python_sdk-0.0.93.dist-info/entry_points.txt
mw_python_sdk-0.0.93.dist-info/RECORD
