Metadata-Version: 2.1
Name: mw-python-sdk
Version: 0.0.93
Summary: ModelWhale Python SDK
Home-page: https://github.com/Kesci/mw-python-sdk
Author: ModelWhale Developers
Author-email: dev@heywhale.com
Requires-Python: >=3.10,<4.0
Classifier: Operating System :: OS Independent
Classifier: Programming Language :: Python :: 3
Classifier: Programming Language :: Python :: 3.10
Classifier: Programming Language :: Python :: 3.11
Classifier: Programming Language :: Python :: 3.12
Classifier: Programming Language :: Python :: 3.13
Provides-Extra: fs
Provides-Extra: llm
Provides-Extra: test
Requires-Dist: PyJWT
Requires-Dist: boto3 (>=1.38.39,<2.0.0)
Requires-Dist: python-dotenv
Requires-Dist: requests
Requires-Dist: requests_unixsocket
Requires-Dist: sseclient-py
Requires-Dist: toml
Requires-Dist: tqdm ; extra == "llm"
Requires-Dist: typer
Project-URL: Documentation, https://github.com/Kesci/mw-python-sdk
Project-URL: Repository, https://github.com/Kesci/mw-python-sdk
